excel_convertor/__init__.py
excel_convertor/excel_convertor.py
excel_convertor-1.4.3.dist-info/licenses/LICENSE
excel_convertor-1.4.3.dist-info/licenses/NOTICE
excel_convertor-1.4.3.dist-info/METADATA
excel_convertor-1.4.3.dist-info/WHEEL
excel_convertor-1.4.3.dist-info/top_level.txt
excel_convertor-1.4.3.dist-info/RECORD
