Metadata-Version: 2.4
Name: excel-convertor
Version: 1.4.3
Summary: 엑셀 생성기 from dictionary
Author-email: Yu Jeonghoon <jeonghoon@jnghn.xyz>
License: MIT License
Project-URL: Homepage, https://github.com/moning02004/excel-convertor
Project-URL: Bug Tracker, https://github.com/moning02004/excel-convertor/issues
Keywords: excel,xlsx,dict,json,python
Requires-Python: >=3.8
License-File: LICENSE
License-File: NOTICE
Requires-Dist: XlsxWriter>=3.0.0
Dynamic: license-file
